sqlalchemy_hawq/__init__.py
sqlalchemy_hawq/ddl.py
sqlalchemy_hawq/dialect.py
sqlalchemy_hawq/partition.py
sqlalchemy_hawq/point.py
test/__init__.py
test/conftest.py
test/requirements.py
test/test_create_all.py
test/test_ddl.py
test/test_live_connection.py
test/test_suite.py
sqlalchemy_hawq-1.0.3.dist-info/LICENSE
sqlalchemy_hawq-1.0.3.dist-info/METADATA
sqlalchemy_hawq-1.0.3.dist-info/WHEEL
sqlalchemy_hawq-1.0.3.dist-info/dependency_links.txt
sqlalchemy_hawq-1.0.3.dist-info/entry_points.txt
sqlalchemy_hawq-1.0.3.dist-info/top_level.txt
sqlalchemy_hawq-1.0.3.dist-info/RECORD
