Metadata-Version: 2.1
Name: sqlalchemy-hawq
Version: 1.0.3
Summary: UNKNOWN
Home-page: UNKNOWN
Author-email: dat@bcgsc.ca
Maintainer: vardb
Maintainer-email: dat@bcgsc.ca
License: UNKNOWN
Platform: UNKNOWN
Classifier: Programming Language :: Python :: 3.7
Classifier: Programming Language :: Python :: 3.8
Classifier: Programming Language :: Python :: 3.9
Classifier: Programming Language :: Python :: 3.10
Classifier: License :: OSI Approved :: MIT License
Requires-Python: >=3.7.1
Requires-Dist: SQLAlchemy (>2)
Requires-Dist: psycopg2-binary
Provides-Extra: deploy
Requires-Dist: wheel ; extra == 'deploy'
Requires-Dist: twine ; extra == 'deploy'
Provides-Extra: dev
Requires-Dist: pytest (>7.1) ; extra == 'dev'
Requires-Dist: pytest-cov ; extra == 'dev'
Requires-Dist: mock ; extra == 'dev'
Requires-Dist: pytest-xdist ; extra == 'dev'
Requires-Dist: wheel ; extra == 'dev'
Requires-Dist: twine ; extra == 'dev'
Requires-Dist: flake8 ; extra == 'dev'
Requires-Dist: black ; extra == 'dev'
Provides-Extra: test
Requires-Dist: pytest (>7.1) ; extra == 'test'
Requires-Dist: pytest-cov ; extra == 'test'
Requires-Dist: mock ; extra == 'test'
Requires-Dist: pytest-xdist ; extra == 'test'
